LICENSE.txt
MANIFEST.in
README.rst
setup.py
autotask/__init__.py
autotask/admin.py
autotask/apps.py
autotask/conf.py
autotask/cron.py
autotask/models.py
autotask/tasks.py
autotask/workers.py
autotask.egg-info/PKG-INFO
autotask.egg-info/SOURCES.txt
autotask.egg-info/dependency_links.txt
autotask.egg-info/not-zip-safe
autotask.egg-info/top_level.txt
autotask/management/__init__.py
autotask/management/commands/__init__.py
autotask/management/commands/run_autotask.py
autotask/migrations/0001_initial.py
autotask/migrations/__init__.py
autotask/test/test_cron.py
autotask/test/test_tasks.py