Metadata-Version: 1.1
Name: autotask
Version: 0.5.4
Summary: A django-application for handling asynchronous tasks.
Home-page: https://bitbucket.org/kbr/autotask
Author: Klaus Bremer
Author-email: bremer@bremer-media.de
License: MIT
Keywords: django-application autotask asynchron
Platform: UNKNOWN
Classifier: Development Status :: 4 - Beta
Classifier: Environment :: Web Environment
Classifier: Framework :: Django
Classifier: Intended Audience :: Developers
Classifier: License :: OSI Approved :: MIT License
Classifier: Natural Language :: English
Classifier: Programming Language :: Python
Classifier: Programming Language :: Python :: 2.7
Classifier: Programming Language :: Python :: 3.4
Classifier: Programming Language :: Python :: 3.5
